<?xml version="1.0" encoding="utf-8"?><toc><breadcrumbs><li><a href="027d2fbc-7bfb-4dc3-b4f5-85f95fcf7629.htm">Spell Checker</a></li><li><a href="e65c2751-130e-5bdb-8507-b19154eefebe.htm">Visual<wbr />Studio.<wbr />Spell<wbr />Checker.<wbr />Definitions</a></li><li><a href="797db4ab-e0e3-0847-5944-353fce7448c6.htm">ISpelling<wbr />Suggestion</a></li></breadcrumbs><tocItems><li><a id="9fb1c75e-f99c-bc2a-0401-a2643322866b" class="has-submenu" href="9fb1c75e-f99c-bc2a-0401-a2643322866b.htm"><span data-tocFile="../toc/IDADQ.xml" class="icon toggle" onclick="ToggleExpandCollapse(this); return false;"><i class="fa fa-angle-right"> </i></span>Properties</a><ul class="toc-menu is-hidden"> </ul></li></tocItems></toc>