<?xml version="1.0" encoding="utf-8"?><toc><breadcrumbs><li><a href="84784fc0-1a4e-4780-9a61-4abfda5592c1.htm">PDI</a></li><li><a href="884ef7d4-95a5-f088-0d55-32fbfec87e77.htm">EWSoftware.<wbr />PDI.<wbr />Properties</a></li><li><a href="24c1194f-7297-3177-f490-4c4eaeb1b603.htm">Product<wbr />Id<wbr />Property</a></li></breadcrumbs><tocItems><li><a id="71ed54cc-996d-2461-41ea-7a1efa07a43c" href="71ed54cc-996d-2461-41ea-7a1efa07a43c.htm">Constructor</a></li><li><a id="707e52e0-4ed3-087c-ff43-9fae70434aef" class="has-submenu" href="707e52e0-4ed3-087c-ff43-9fae70434aef.htm"><span data-tocFile="../toc/IDB0MC0K.xml" class="icon toggle" onclick="ToggleExpandCollapse(this); return false;"><i class="fa fa-angle-right"> </i></span>Properties</a><ul class="toc-menu is-hidden"> </ul></li><li><a id="b4983fb8-4226-033d-236f-c3b38034050d" class="has-submenu" href="b4983fb8-4226-033d-236f-c3b38034050d.htm"><span data-tocFile="../toc/IDC0MC0K.xml" class="icon toggle" onclick="ToggleExpandCollapse(this); return false;"><i class="fa fa-angle-right"> </i></span>Methods</a><ul class="toc-menu is-hidden"> </ul></li></tocItems></toc>